{"brand":["代言人","開幕","保固","贊助"],
"brand_season":["女人節","情人節","兒童節","母親節","清明節","櫻花季","掃墓","和平紀念日","228","母親"],
"social_rspns":["地球","環保","育幼院","環境","心力","愛心"],
"engage_assist":["如何","學問","參考","建議","食譜","感謝","謝謝","課程","分享","好選擇","好去處","好方法","去處","方法","知識","觀念","新知","小常識","常識","tips","tip","Tips","Tip","提示","技巧","小提示","小技巧"],
"engage_social":["截圖","有獎徵答","按下","點擊","點圖","按讚","按愛心","留言","tag好友","Tag好友","tag朋友","Tag朋友","Tag","tag","標記","打卡","問卷","投票","票選"],
"engage_inter":["測驗","答案","想問","告訴我們","告訴小編","比賽","請問","上傳","下載","答對","互動","搶答","回答","猜出","猜猜看","猜猜","遊戲","直播","報名","追蹤"],
"product_new":["新一代","全新","新型","新品","新貨","新品上市","上市","推出","預購","開賣","預購","預約","新口味","新上市","上架","更新"],
"product_version":["系列","全系列","歐系","日系","美系","特別版","進化版","限定版","升級版","限量版","聯名","合作","車系","車型","引擎","期間限定","經典","聯名","造型","這一代","上一代","設計","最新版"],
"product_test":["部落客","試用","試吃","開箱","試駕","試乘","入主","入手","鑑賞","cp值","CP值","體驗"],
"product_unit":["聖品","單品","產品","性能","商品","口味","鞋款","分享餐","功能","效能"],
"promo_deal":["禮物","抵用券","再送","優惠券","贈品","禮券","發送","特價","好康","優惠","半價","得獎者","得獎","獎項","特惠","優惠","買就送","拿好禮","滿額贈","折價券","贈完為止","送完為止","售完為止","抽出","抽中","抽獎","大獎","折扣","好禮","抽好禮","加送","買一送一","加贈","回饋","贈送","來店禮","現折","現抵","機會","中獎","優惠活動","第二杯半價","免費","集點換","獎金","滿額","幸運兒","領獎","省錢","省最多","獎品"],
"promo_discnt":["1折","2折","3折","4折","5折","6折","7折","8折","9折","65折","75折","85折","95折","一折","二折","兩折","三折","四折","五折","六折","七折","八折","九折","六五折","七五折","八五折","九五折","促銷價"]}